{
  "type": "minecraft:entity",
  "pools": [
    {
      "rolls": 1,
      "entries": [
        {
          "type": "minecraft:loot_table",
          "name": "vanilla:entities/pillager"
        }
      ]
    },
    {
      "rolls": 1,
      "entries": [
        {
          "type": "minecraft:alternatives",
          "children": [
            {
              "type": "minecraft:item",
              "name": "player_head",
              "weight": 1,
              "functions": [
                {
                  "function": "minecraft:set_nbt",
                  "tag": "{SkullOwner:{Id:[I;339350619,22694589,-1314296442,1663701461],Name:\"Bad Omen Pillager\",Properties:{textures:[{Value:\"eyJ0ZXh0dXJlcyI6eyJTS0lOIjp7InVybCI6Imh0dHA6Ly90ZXh0dXJlcy5taW5lY3JhZnQubmV0L3RleHR1cmUvMzQ1NDNlM2RmYjUwNDhiNDNjYTNjM2FiY2YwZGY0YjNmY2ZiMTdhOTk4NTRkNzZjZmFhNjdhNjYxZjU2NGZkOSJ9fX0=\"}]}}}"
                }
              ],
              "conditions": [
                {
                  "condition": "minecraft:entity_properties",
                  "entity": "this",
                  "predicate": {
                    "nbt": "{ArmorItems:[{},{},{},{id:\"minecraft:white_banner\",Count:1b,tag:{HideFlags:32,BlockEntityTag:{Patterns:[{Pattern:\"mr\",Color:9},{Pattern:\"bs\",Color:8},{Pattern:\"cs\",Color:7},{Pattern:\"bo\",Color:8},{Pattern:\"ms\",Color:15},{Pattern:\"hh\",Color:8},{Pattern:\"mc\",Color:8},{Pattern:\"bo\",Color:15}]},display:{Name:'{\"color\":\"gold\",\"translate\":\"block.minecraft.ominous_banner\"}'}}}],PatrolLeader:1b,Wave:0}"
                  }
                }
              ]
            },
            {
              "type": "minecraft:item",
              "name": "minecraft:player_head",
              "weight": 1,
              "functions": [
                {
                  "function": "minecraft:set_nbt",
                  "tag": "{SkullOwner:{Id:[I;1339570758,-1965080213,-1455428410,-985047630],Name:\"Pillager\",Properties:{textures:[{Value:\"eyJ0ZXh0dXJlcyI6eyJTS0lOIjp7InVybCI6Imh0dHA6Ly90ZXh0dXJlcy5taW5lY3JhZnQubmV0L3RleHR1cmUvYzIyNWYwYjQ5YzUyOTUwNDhhNDA5YzljNjAxY2NhNzlhYThlYjUyYWZmNWUyMDMzZWJiODY1ZjQzNjdlZjQzZSJ9fX0=\"}]}}}"
                }
              ]
            }
          ]
        }
      ],
      "conditions": [
        {
          "condition": "minecraft:alternative",
          "terms": [
            {
              "condition": "minecraft:inverted",
              "term": {
                "condition": "minecraft:alternative",
                "terms": [
                  {
                    "condition": "minecraft:inverted",
                    "term": {
                      "condition": "minecraft:random_chance_with_looting",
                      "chance": 0.035,
                      "looting_multiplier": 0.005
                    }
                  },
                  {
                    "condition": "minecraft:inverted",
                    "term": {
                      "condition": "minecraft:killed_by_player",
                      "inverse": false
                    }
                  }
                ]
              }
            },
            {
              "condition": "minecraft:damage_source_properties",
              "predicate": {
                "is_explosion": true,
                "source_entity": {
                  "type": "minecraft:creeper",
                  "nbt": "{powered:1b}"
                }
              }
            }
          ]
        }
      ]
    }
  ]
}